mapillary_tools/__init__.py
mapillary_tools/api_v4.py
mapillary_tools/authenticate.py
mapillary_tools/blackvue_parser.py
mapillary_tools/config.py
mapillary_tools/constants.py
mapillary_tools/exceptions.py
mapillary_tools/exif_read.py
mapillary_tools/exif_write.py
mapillary_tools/exiftool_read.py
mapillary_tools/exiftool_read_video.py
mapillary_tools/exiftool_runner.py
mapillary_tools/ffmpeg.py
mapillary_tools/geo.py
mapillary_tools/history.py
mapillary_tools/http.py
mapillary_tools/ipc.py
mapillary_tools/process_geotag_properties.py
mapillary_tools/process_sequence_properties.py
mapillary_tools/sample_video.py
mapillary_tools/store.py
mapillary_tools/telemetry.py
mapillary_tools/types.py
mapillary_tools/upload.py
mapillary_tools/upload_api_v4.py
mapillary_tools/uploader.py
mapillary_tools/utils.py
mapillary_tools/camm/camm_builder.py
mapillary_tools/camm/camm_parser.py
mapillary_tools/commands/__init__.py
mapillary_tools/commands/__main__.py
mapillary_tools/commands/authenticate.py
mapillary_tools/commands/process.py
mapillary_tools/commands/process_and_upload.py
mapillary_tools/commands/sample_video.py
mapillary_tools/commands/upload.py
mapillary_tools/commands/video_process.py
mapillary_tools/commands/video_process_and_upload.py
mapillary_tools/commands/zip.py
mapillary_tools/geotag/__init__.py
mapillary_tools/geotag/base.py
mapillary_tools/geotag/factory.py
mapillary_tools/geotag/geotag_images_from_exif.py
mapillary_tools/geotag/geotag_images_from_exiftool.py
mapillary_tools/geotag/geotag_images_from_gpx.py
mapillary_tools/geotag/geotag_images_from_gpx_file.py
mapillary_tools/geotag/geotag_images_from_nmea_file.py
mapillary_tools/geotag/geotag_images_from_video.py
mapillary_tools/geotag/geotag_videos_from_exiftool.py
mapillary_tools/geotag/geotag_videos_from_gpx.py
mapillary_tools/geotag/geotag_videos_from_video.py
mapillary_tools/geotag/options.py
mapillary_tools/geotag/utils.py
mapillary_tools/geotag/image_extractors/base.py
mapillary_tools-0.14.5.dist-info/licenses/LICENSE
mapillary_tools-0.14.5.dist-info/METADATA
mapillary_tools-0.14.5.dist-info/WHEEL
mapillary_tools-0.14.5.dist-info/entry_points.txt
mapillary_tools-0.14.5.dist-info/top_level.txt
mapillary_tools-0.14.5.dist-info/RECORD
