Metadata-Version: 2.4
Name: mapillary_tools
Version: 0.14.5
Summary: Mapillary Image/Video Import Pipeline
Author-email: Mapillary <support@mapillary.com>
License: BSD
Project-URL: Homepage, https://github.com/mapillary/mapillary_tools
Project-URL: Repository, https://github.com/mapillary/mapillary_tools
Project-URL: Issues, https://github.com/mapillary/mapillary_tools/issues
Keywords: mapillary,gis,computer vision,street view
Classifier: Development Status :: 5 - Production/Stable
Classifier: Intended Audience :: Developers
Classifier: Intended Audience :: End Users/Desktop
Classifier: License :: OSI Approved :: BSD License
Classifier: Programming Language :: Python :: 3
Classifier: Programming Language :: Python :: 3.9
Classifier: Programming Language :: Python :: 3.10
Classifier: Programming Language :: Python :: 3.11
Classifier: Programming Language :: Python :: 3.12
Classifier: Programming Language :: Python :: 3.13
Requires-Python: >=3.9
License-File: LICENSE
Requires-Dist: appdirs<2.0.0,>=1.4.4
Requires-Dist: construct~=2.10.0
Requires-Dist: exifread~=3.0
Requires-Dist: gpxpy~=1.6.0
Requires-Dist: humanize>=4.12.3
Requires-Dist: jsonschema~=4.17.0
Requires-Dist: piexif~=1.1
Requires-Dist: pynmea2<2.0.0,>=1.12.0
Requires-Dist: requests[socks]<3.0.0,>=2.20.0
Requires-Dist: tqdm<5.0,>=4.0
Requires-Dist: typing-extensions>=4.12.2
Dynamic: license-file
